<?xml version="1.0" encoding="UTF-8" ?>
<dataroot>
  <OrderLine>
    <OrderNum>21608</OrderNum>
    <PartNum>AT94</PartNum>
    <NumOrdered>11</NumOrdered>
    <QuotedPrice>21.95</QuotedPrice>
  </OrderLine>
  <OrderLine>
    <OrderNum>21610</OrderNum>
    <PartNum>DR93</PartNum>
    <NumOrdered>1</NumOrdered>
    <QuotedPrice>495.00</QuotedPrice>
  </OrderLine>
  <OrderLine>
    <OrderNum>21610</OrderNum>
    <PartNum>DW11</PartNum>
    <NumOrdered>1</NumOrdered>
    <QuotedPrice>399.99</QuotedPrice>
  </OrderLine>
  <OrderLine>
    <OrderNum>21613</OrderNum>
    <PartNum>KL62</PartNum>
    <NumOrdered>4</NumOrdered>
    <QuotedPrice>329.95</QuotedPrice>
  </OrderLine>
  <OrderLine>
    <OrderNum>21614</OrderNum>
    <PartNum>KT03</PartNum>
    <NumOrdered>2</NumOrdered>
    <QuotedPrice>595.00</QuotedPrice>
  </OrderLine>
  <OrderLine>
    <OrderNum>21617</OrderNum>
    <PartNum>BV06</PartNum>
    <NumOrdered>2</NumOrdered>
    <QuotedPrice>794.95</QuotedPrice>
  </OrderLine>
  <OrderLine>
    <OrderNum>21617</OrderNum>
    <PartNum>CD52</PartNum>
    <NumOrdered>4</NumOrdered>
    <QuotedPrice>150.00</QuotedPrice>
  </OrderLine>
  <OrderLine>
    <OrderNum>21619</OrderNum>
    <PartNum>DR93</PartNum>
    <NumOrdered>1</NumOrdered>
    <QuotedPrice>495.00</QuotedPrice>
  </OrderLine>
  <OrderLine>
    <OrderNum>21623</OrderNum>
    <PartNum>KV29</PartNum>
    <NumOrdered>2</NumOrdered>
    <QuotedPrice>1290.00</QuotedPrice>
  </OrderLine>
</dataroot>
